Workbook

Sheet IBM HR Analytics Cleaned
A1: Age | B1: Attrition | C1: BusinessTravel | D1: DailyRate | E1: Department | F1: DistanceFromHome | G1: Education | H1: EducationField | I1: EmployeeNumber | J1: EnvironmentSatisfaction | K1: Gender | L1: HourlyRate | M1: JobInvolvement | N1: JobLevel | O1: JobRole | P1: JobSatisfaction | Q1: MaritalStatus | R1: MonthlyIncome | S1: MonthlyRate | T1: NumCompaniesWorked | U1: OverTime | V1: PercentSalaryHike | W1: PerformanceRating | X1: RelationshipSatisfaction | Y1: StockOptionLevel | Z1: TotalWorkingYears | AA1: TrainingTimesLastYear | AB1: WorkLifeBalance | AC1: YearsAtCompany | AD1: YearsInCurrentRole | AE1: YearsSinceLastPromotion | AF1: YearsWithCurrManager | AG1: AgeGroup | AH1: SalaryBand | AI1: AttritionFlag | AJ1: TenureBand | AK1: EducationLabel | AL1: JobSatisfactionLabel | AM1: WorkLifeBalanceLabel | AN1: RiskScore
A2: 41 | B2: Yes | C2: Travel_Rarely | D2: 1102 | E2: Sales | F2: 1 | G2: 2 | H2: Life Sciences | I2: 1 | J2: 2 | K2: Female | L2: 94 | M2: 3 | N2: 2 | O2: Sales Executive | P2: 4 | Q2: Single | R2: 5993 | S2: 19479 | T2: 8 | U2: Yes | V2: 11 | W2: 3 | X2: 1 | Y2: 0 | Z2: 8 | AA2: 0 | AB2: 1 | AC2: 6 | AD2: 4 | AE2: 0 | AF2: 5 | AG2: 36-45 | AH2: Very High (>10K) | AI2: 1 | AJ2: 0-2 yrs | AK2: College | AL2: Very High | AM2: Bad | AN2: =((3-P2)*3+((3-AB2)*2+AE2)) -> 1
A3: 49 | B3: No | C3: Travel_Frequently | D3: 279 | E3: Research & Development | F3: 8 | G3: 1 | H3: Life Sciences | I3: 2 | J3: 3 | K3: Male | L3: 61 | M3: 2 | N3: 2 | O3: Research Scientist | P3: 2 | Q3: Married | R3: 5130 | S3: 24907 | T3: 1 | U3: No | V3: 23 | W3: 4 | X3: 4 | Y3: 1 | Z3: 10 | AA3: 3 | AB3: 3 | AC3: 10 | AD3: 7 | AE3: 1 | AF3: 7 | AG3: 46-60 | AH3: Very High (>10K) | AI3: 0 | AJ3: 6-10 yrs | AK3: Below College | AL3: Medium | AM3: Better | AN3: =((3-P3)*3+((3-AB3)*2+AE3)) -> 4
A4: 37 | B4: Yes | C4: Travel_Rarely | D4: 1373 | E4: Research & Development | F4: 2 | G4: 2 | H4: Other | I4: 4 | J4: 4 | K4: Male | L4: 92 | M4: 2 | N4: 1 | O4: Laboratory Technician | P4: 3 | Q4: Single | R4: 2090 | S4: 2396 | T4: 6 | U4: Yes | V4: 15 | W4: 3 | X4: 2 | Y4: 0 | Z4: 7 | AA4: 3 | AB4: 3 | AC4: 0 | AD4: 0 | AE4: 0 | AF4: 0 | AG4: 36-45 | AH4: Low (≤3K) | AI4: 1 | AJ4: 3-5 yrs | AK4: College | AL4: High | AM4: Better | AN4: =((3-P4)*3+((3-AB4)*2+AE4)) -> 0
A5: 33 | B5: No | C5: Travel_Frequently | D5: 1392 | E5: Research & Development | F5: 3 | G5: 4 | H5: Life Sciences | I5: 5 | J5: 4 | K5: Female | L5: 56 | M5: 3 | N5: 1 | O5: Research Scientist | P5: 3 | Q5: Married | R5: 2909 | S5: 23159 | T5: 1 | U5: Yes | V5: 11 | W5: 3 | X5: 3 | Y5: 0 | Z5: 8 | AA5: 3 | AB5: 3 | AC5: 8 | AD5: 7 | AE5: 3 | AF5: 0 | AG5: 26-35 | AH5: Very High (>10K) | AI5: 0 | AJ5: 6-10 yrs | AK5: Master | AL5: High | AM5: Better | AN5: =((3-P5)*3+((3-AB5)*2+AE5)) -> 3
A6: 27 | B6: No | C6: Travel_Rarely | D6: 591 | E6: Research & Development | F6: 2 | G6: 1 | H6: Medical | I6: 7 | J6: 1 | K6: Male | L6: 40 | M6: 3 | N6: 1 | O6: Laboratory Technician | P6: 2 | Q6: Married | R6: 3468 | S6: 16632 | T6: 9 | U6: No | V6: 12 | W6: 3 | X6: 4 | Y6: 1 | Z6: 6 | AA6: 3 | AB6: 3 | AC6: 2 | AD6: 2 | AE6: 2 | AF6: 2 | AG6: 26-35 | AH6: Very High (>10K) | AI6: 0 | AJ6: 3-5 yrs | AK6: Below College | AL6: Medium | AM6: Better | AN6: =((3-P6)*3+((3-AB6)*2+AE6)) -> 5
A7: 32 | B7: No | C7: Travel_Frequently | D7: 1005 | E7: Research & Development | F7: 2 | G7: 2 | H7: Life Sciences | I7: 8 | J7: 4 | K7: Male | L7: 79 | M7: 3 | N7: 1 | O7: Laboratory Technician | P7: 4 | Q7: Single | R7: 3068 | S7: 11864 | T7: 0 | U7: No | V7: 13 | W7: 3 | X7: 3 | Y7: 0 | Z7: 8 | AA7: 2 | AB7: 2 | AC7: 7 | AD7: 7 | AE7: 3 | AF7: 6 | AG7: 26-35 | AH7: Very High (>10K) | AI7: 0 | AJ7: 0-2 yrs | AK7: College | AL7: Very High | AM7: Good | AN7: =((3-P7)*3+((3-AB7)*2+AE7)) -> 2
A8: 59 | B8: No | C8: Travel_Rarely | D8: 1324 | E8: Research & Development | F8: 3 | G8: 3 | H8: Medical | I8: 10 | J8: 3 | K8: Female | L8: 81 | M8: 4 | N8: 1 | O8: Laboratory Technician | P8: 1 | Q8: Married | R8: 2670 | S8: 9964 | T8: 4 | U8: Yes | V8: 20 | W8: 4 | X8: 1 | Y8: 3 | Z8: 12 | AA8: 3 | AB8: 2 | AC8: 1 | AD8: 0 | AE8: 0 | AF8: 0 | AG8: 46-60 | AH8: High (6K-10K) | AI8: 0 | AJ8: 0-2 yrs | AK8: Bachelor | AL8: Low | AM8: Good | AN8: =((3-P8)*3+((3-AB8)*2+AE8)) -> 8
A9: 30 | B9: No | C9: Travel_Rarely | D9: 1358 | E9: Research & Development | F9: 24 | G9: 1 | H9: Life Sciences | I9: 11 | J9: 4 | K9: Male | L9: 67 | M9: 3 | N9: 1 | O9: Laboratory Technician | P9: 3 | Q9: Divorced | R9: 2693 | S9: 13335 | T9: 1 | U9: No | V9: 22 | W9: 4 | X9: 2 | Y9: 1 | Z9: 1 | AA9: 2 | AB9: 3 | AC9: 1 | AD9: 0 | AE9: 0 | AF9: 0 | AG9: 26-35 | AH9: Very High (>10K) | AI9: 0 | AJ9: 3-5 yrs | AK9: Below College | AL9: High | AM9: Better | AN9: =((3-P9)*3+((3-AB9)*2+AE9)) -> 0
A10: 38 | B10: No | C10: Travel_Frequently | D10: 216 | E10: Research & Development | F10: 23 | G10: 3 | H10: Life Sciences | I10: 12 | J10: 4 | K10: Male | L10: 44 | M10: 2 | N10: 3 | O10: Manufacturing Director | P10: 3 | Q10: Single | R10: 9526 | S10: 8787 | T10: 0 | U10: No | V10: 21 | W10: 4 | X10: 2 | Y10: 0 | Z10: 10 | AA10: 2 | AB10: 3 | AC10: 9 | AD10: 7 | AE10: 1 | AF10: 8 | AG10: 36-45 | AH10: High (6K-10K) | AI10: 0 | AJ10: 6-10 yrs | AK10: Bachelor | AL10: High | AM10: Better | AN10: =((3-P10)*3+((3-AB10)*2+AE10)) -> 1
A11: 36 | B11: No | C11: Travel_Rarely | D11: 1299 | E11: Research & Development | F11: 27 | G11: 3 | H11: Medical | I11: 13 | J11: 3 | K11: Male | L11: 94 | M11: 3 | N11: 2 | O11: Healthcare Representative | P11: 3 | Q11: Married | R11: 5237 | S11: 16577 | T11: 6 | U11: No | V11: 13 | W11: 3 | X11: 2 | Y11: 2 | Z11: 17 | AA11: 3 | AB11: 2 | AC11: 7 | AD11: 7 | AE11: 7 | AF11: 7 | AG11: 36-45 | AH11: Very High (>10K) | AI11: 0 | AJ11: 0-2 yrs | AK11: Bachelor | AL11: High | AM11: Good | AN11: =((3-P11)*3+((3-AB11)*2+AE11)) -> 9
A12: 35 | B12: No | C12: Travel_Rarely | D12: 809 | E12: Research & Development | F12: 16 | G12: 3 | H12: Medical | I12: 14 | J12: 1 | K12: Male | L12: 84 | M12: 4 | N12: 1 | O12: Laboratory Technician | P12: 2 | Q12: Married | R12: 2426 | S12: 16479 | T12: 0 | U12: No | V12: 13 | W12: 3 | X12: 3 | Y12: 1 | Z12: 6 | AA12: 5 | AB12: 3 | AC12: 5 | AD12: 4 | AE12: 0 | AF12: 3 | AG12: 26-35 | AH12: Very High (>10K) | AI12: 0 | AJ12: 3-5 yrs | AK12: Bachelor | AL12: Medium | AM12: Better | AN12: =((3-P12)*3+((3-AB12)*2+AE12)) -> 3
A13: 29 | B13: No | C13: Travel_Rarely | D13: 153 | E13: Research & Development | F13: 15 | G13: 2 | H13: Life Sciences | I13: 15 | J13: 4 | K13: Female | L13: 49 | M13: 2 | N13: 2 | O13: Laboratory Technician | P13: 3 | Q13: Single | R13: 4193 | S13: 12682 | T13: 0 | U13: Yes | V13: 12 | W13: 3 | X13: 4 | Y13: 0 | Z13: 10 | AA13: 3 | AB13: 3 | AC13: 9 | AD13: 5 | AE13: 0 | AF13: 8 | AG13: 26-35 | AH13: Very High (>10K) | AI13: 0 | AJ13: 6-10 yrs | AK13: College | AL13: High | AM13: Better | AN13: =((3-P13)*3+((3-AB13)*2+AE13)) -> 0
... A1471: 34 | B1471: No | C1471: Travel_Rarely | D1471: 628 | E1471: Research & Development | F1471: 8 | G1471: 3 | H1471: Medical | I1471: 2068 | J1471: 2 | K1471: Male | L1471: 82 | M1471: 4 | N1471: 2 | O1471: Laboratory Technician | P1471: 3 | Q1471: Married | R1471: 4404 | S1471: 10228 | T1471: 2 | U1471: No | V1471: 12 | W1471: 3 | X1471: 1 | Y1471: 0 | Z1471: 6 | AA1471: 3 | AB1471: 4 | AC1471: 4 | AD1471: 3 | AE1471: 1 | AF1471: 2 | AG1471: 26-35 | AH1471: Very High (>10K) | AI1471: 0 | AJ1471: 3-5 yrs | AK1471: Bachelor | AL1471: High | AM1471: Best | AN1471: =((3-P1471)*3+((3-AB1471)*2+AE1471)) -> -1

Sheet Dashboard
E1: HR ANALYTICS DASHBOARD — IBM Employee Dataset
E2: Attrition | Salary | Satisfaction | Tenure Analysis | 1,470 Employees | 3 Departments | 9 Job Roles
E6: TOTAL EMPLOYEES | F6: ATTRITION RATE | G6: AVG MONTHLY INCOME | H6: AVG AGE
E7: =COUNTA('IBM HR Analytics Cleaned'!A:A)-1 -> 1470 | F7: =COUNTIF('IBM HR Analytics Cleaned'!B2:B1471,"Yes")/COUNTA('IBM HR Analytics Cleaned'!B2:B1471) -> 0.16122449 | G7: =AVERAGE('IBM HR Analytics Cleaned'!R2:R1471) -> 6502.9313 | H7: =AVERAGE('IBM HR Analytics Cleaned'!A2:A1471) -> 36.92381
E10: ACTIVE EMPLOYEES | F10: ATTRITED EMPLOYEES | G10: AVG TENURE | H10: HIGH RISK STAFF
E11: =COUNTIF('IBM HR Analytics Cleaned'!B2:B1471,"No") -> 1233 | F11: =COUNTIF('IBM HR Analytics Cleaned'!B2:B1471,"Yes") -> 237 | G11: =AVERAGE('IBM HR Analytics Cleaned'!AC2:AC1471) -> 7.0081633 | H11: 97

Sheet Attrition Analysis
C1: ATTRITION DEEP-DIVE ANALYSIS
C2: Department · Age Group · Tenure · Business Travel · Job Satisfaction · Work-Life Balance
C5: Attrition by Department | H5: Attrition by Age Group | M5: Attrition by Tenure
C6: Department | D6: Total | E6: Attrited | F6: Attrition rate | H6: Age Group | I6: Total | J6: Attrited | K6: Attrition rate | M6: Tenure Band | N6: Total | O6: Attrited | P6: Attrition %
C7: Human Resources | D7: 63 | E7: 12 | F7: =GETPIVOTDATA("Attrited",$C$6,"Department","Human Resources")/GETPIVOTDATA("Total",$C$6,"Department","Human Resources") -> 0.19047619 | H7: 18-25 | I7: 123 | J7: 44 | K7: =GETPIVOTDATA("Attrited",$H$6,"AgeGroup","18-25")/GETPIVOTDATA("Total",$H$6,"AgeGroup","18-25") -> 0.35772358 | M7: 0-2 yrs | N7: 424 | O7: 83 | P7: =GETPIVOTDATA("Attrited",$M$6,"TenureBand","0-2 yrs")/GETPIVOTDATA("Total",$M$6,"TenureBand","0-2 yrs") -> 0.19575472
C8: Research & Development | D8: 961 | E8: 133 | F8: =GETPIVOTDATA("Attrited",$C$6,"Department","Research & Development")/GETPIVOTDATA("Total",$C$6,"Department","Research & Development") -> 0.1383975 | H8: 26-35 | I8: 606 | J8: 116 | K8: =GETPIVOTDATA("Attrited",$H$6,"AgeGroup","26-35")/GETPIVOTDATA("Total",$H$6,"AgeGroup","26-35") -> 0.19141914 | M8: 10+ yrs | N8: 178 | O8: 13 | P8: =GETPIVOTDATA("Attrited",$M$6,"TenureBand","10+ yrs")/GETPIVOTDATA("Total",$M$6,"TenureBand","10+ yrs") -> 0.073033708
C9: Sales | D9: 446 | E9: 92 | F9: =GETPIVOTDATA("Attrited",$C$6,"Department","Sales")/GETPIVOTDATA("Total",$C$6,"Department","Sales") -> 0.20627803 | H9: 36-45 | I9: 468 | J9: 43 | K9: =GETPIVOTDATA("Attrited",$H$6,"AgeGroup","36-45")/GETPIVOTDATA("Total",$H$6,"AgeGroup","36-45") -> 0.091880342 | M9: 3-5 yrs | N9: 556 | O9: 108 | P9: =GETPIVOTDATA("Attrited",$M$6,"TenureBand","3-5 yrs")/GETPIVOTDATA("Total",$M$6,"TenureBand","3-5 yrs") -> 0.1942446
C10: Grand Total | D10: 1470 | E10: 237 | H10: 46-60 | I10: 273 | J10: 34 | K10: =GETPIVOTDATA("Attrited",$H$6,"AgeGroup","46-60")/GETPIVOTDATA("Total",$H$6,"AgeGroup","46-60") -> 0.12454212 | M10: 6-10 yrs | N10: 312 | O10: 33 | P10: =GETPIVOTDATA("Attrited",$M$6,"TenureBand","6-10 yrs")/GETPIVOTDATA("Total",$M$6,"TenureBand","6-10 yrs") -> 0.10576923
H11: Grand Total | I11: 1470 | J11: 237 | M11: Grand Total | N11: 1470 | O11: 237
C13: Attrition by Business Travel | H13: Attrition by Job Satisfaction | M13: Attrition by Work-Life Balance
C14: Business Travel | D14: Total | E14: Attrited | F14: Attrition rate | H14: Satisfaction | I14: Total | J14: Attrited | K14: Attrition rate | M14: Work Life Balance | N14: Total | O14: Attrited | P14: Attrition %
C15: Non-Travel | D15: 150 | E15: 12 | F15: =GETPIVOTDATA("Attrited",$C$14,"BusinessTravel","Non-Travel")/GETPIVOTDATA("Total",$C$14,"BusinessTravel","Non-Travel") -> 0.08 | H15: High | I15: 442 | J15: 73 | K15: =GETPIVOTDATA("Attrited",$H$14,"JobSatisfactionLabel","High")/GETPIVOTDATA("Total",$H$14,"JobSatisfactionLabel","High") -> 0.16515837 | M15: Bad | N15: 80 | O15: 25 | P15: =GETPIVOTDATA("Attrited",$M$14,"WorkLifeBalance2","Bad")/GETPIVOTDATA("Total",$M$14,"WorkLifeBalance2","Bad") -> 0.3125
C16: Travel_Frequently | D16: 277 | E16: 69 | F16: =GETPIVOTDATA("Attrited",$C$14,"BusinessTravel","Travel_Frequently")/GETPIVOTDATA("Total",$C$14,"BusinessTravel","Travel_Frequently") -> 0.24909747 | H16: Low | I16: 289 | J16: 66 | K16: =GETPIVOTDATA("Attrited",$H$14,"JobSatisfactionLabel","Low")/GETPIVOTDATA("Total",$H$14,"JobSatisfactionLabel","Low") -> 0.2283737 | M16: Best | N16: 153 | O16: 27 | P16: =GETPIVOTDATA("Attrited",$M$14,"WorkLifeBalance2","Best")/GETPIVOTDATA("Total",$M$14,"WorkLifeBalance2","Best") -> 0.17647059
C17: Travel_Rarely | D17: 1043 | E17: 156 | F17: =GETPIVOTDATA("Attrited",$C$14,"BusinessTravel","Travel_Rarely")/GETPIVOTDATA("Total",$C$14,"BusinessTravel","Travel_Rarely") -> 0.14956855 | H17: Medium | I17: 280 | J17: 46 | K17: =GETPIVOTDATA("Attrited",$H$14,"JobSatisfactionLabel","Medium")/GETPIVOTDATA("Total",$H$14,"JobSatisfactionLabel","Medium") -> 0.16428571 | M17: Better | N17: 893 | O17: 127 | P17: =GETPIVOTDATA("Attrited",$M$14,"WorkLifeBalance2","Better")/GETPIVOTDATA("Total",$M$14,"WorkLifeBalance2","Better") -> 0.14221725
C18: Grand Total | D18: 1470 | E18: 237 | H18: Very High | I18: 459 | J18: 52 | K18: =GETPIVOTDATA("Attrited",$H$14,"JobSatisfactionLabel","Very High")/GETPIVOTDATA("Total",$H$14,"JobSatisfactionLabel","Very High") -> 0.11328976 | M18: Good | N18: 344 | O18: 58 | P18: =GETPIVOTDATA("Attrited",$M$14,"WorkLifeBalance2","Good")/GETPIVOTDATA("Total",$M$14,"WorkLifeBalance2","Good") -> 0.16860465
H19: Grand Total | I19: 1470 | J19: 237 | M19: Grand Total | N19: 1470 | O19: 237
C21: Attrition by Overtime | H21: Attrition by Marital Status | M21: Attrition by Gender
C22: Overtime | D22: Total | E22: Attrited | F22: Attrition rate | H22: Marital Status | I22: Total | J22: attrited | K22: Attrition rate | M22: Gender | N22: Total | O22: Attrited | P22: Attrition rate
C23: No | D23: 1054 | E23: 110 | F23: =GETPIVOTDATA("Attrited",$C$22,"OverTime","No")/GETPIVOTDATA("Total",$C$22,"OverTime","No") -> 0.10436433 | H23: Divorced | I23: 327 | J23: 33 | K23: =GETPIVOTDATA("attrited",$H$22,"MaritalStatus","Divorced")/GETPIVOTDATA("Total",$H$22,"MaritalStatus","Divorced") -> 0.10091743 | M23: Female | N23: 588 | O23: 87 | P23: =GETPIVOTDATA("Attrited",$M$22,"Gender","Female")/GETPIVOTDATA("Total",$M$22,"Gender","Female") -> 0.14795918
C24: Yes | D24: 416 | E24: 127 | F24: =GETPIVOTDATA("Attrited",$C$22,"OverTime","Yes")/GETPIVOTDATA("Total",$C$22,"OverTime","Yes") -> 0.30528846 | H24: Married | I24: 673 | J24: 84 | K24: =GETPIVOTDATA("attrited",$H$22,"MaritalStatus","Married")/GETPIVOTDATA("Total",$H$22,"MaritalStatus","Married") -> 0.12481426 | M24: Male | N24: 882 | O24: 150 | P24: =GETPIVOTDATA("Attrited",$M$22,"Gender","Male")/GETPIVOTDATA("Total",$M$22,"Gender","Male") -> 0.17006803
C25: Grand Total | D25: 1470 | E25: 237 | H25: Single | I25: 470 | J25: 120 | K25: =GETPIVOTDATA("attrited",$H$22,"MaritalStatus","Single")/GETPIVOTDATA("Total",$H$22,"MaritalStatus","Single") -> 0.25531915 | M25: Grand Total | N25: 1470 | O25: 237
H26: Grand Total | I26: 1470 | J26: 237

Sheet Salary Analysis
D1: SALARY & COMPENSATION ANALYSIS
D2: Job Role | Department | Salary Band | Education | Job Level | Income Range: $1,009 – $19,999
D5: Average Salary by Job Role | K5: Salary Band Distribution
D6: Job Role | E6: Average Salary | F6: Min Salary | G6: Max Salary | H6: Head Count | K6: Count of EmployeeNumber | L6: Column Labels
D7: Healthcare Representative | E7: 7528.7634 | F7: 4000 | G7: 13966 | H7: 131 | K7: Department | L7: High (6K-10K) | M7: Low (≤3K) | N7: Mid (3K-6K) | O7: Very High (>10K) | P7: Grand Total
D8: Human Resources | E8: 4235.75 | F8: 1555 | G8: 10725 | H8: 52 | K8: Human Resources | L8: 0.23809524 | M8: 0.047619048 | N8: 0.12698413 | O8: 0.58730159 | P8: 1
D9: Laboratory Technician | E9: 3237.1699 | F9: 1102 | G9: 7403 | H9: 259 | K9: Research & Development | L9: 0.16753382 | M9: 0.028095734 | N9: 0.13527575 | O9: 0.66909469 | P9: 1
D10: Manager | E10: 17181.676 | F10: 11244 | G10: 19999 | H10: 102 | K10: Sales | L10: 0.15919283 | M10: 0.040358744 | N10: 0.12107623 | O10: 0.6793722 | P10: 1
D11: Manufacturing Director | E11: 7295.1379 | F11: 4011 | G11: 13973 | H11: 145 | K11: Grand Total | L11: 0.16802721 | M11: 0.032653061 | N11: 0.13061224 | O11: 0.66870748 | P11: 1
D12: Research Director | E12: 16033.55 | F12: 11031 | G12: 19973 | H12: 80
D13: Research Scientist | E13: 3239.9726 | F13: 1009 | G13: 9724 | H13: 292
D14: Sales Executive | E14: 6924.2791 | F14: 4001 | G14: 13872 | H14: 326
D15: Sales Representative | E15: 2626 | F15: 1052 | G15: 6632 | H15: 83
D16: Grand Total | E16: 6502.9313 | F16: 1009 | G16: 19999 | H16: 1470
D21: Salary & Attrition by Job Level
D22: Job level | E22: Total | F22: Average | G22: Attrited | H22: Attrition Rate
D23: 1 | E23: 543 | F23: 2786.9153 | G23: 143 | H23: =GETPIVOTDATA("Attrited",$D$22,"JobLevel",1)/GETPIVOTDATA("Average",$D$22,"JobLevel",1) -> 0.051311212
D24: 2 | E24: 534 | F24: 5502.2772 | G24: 52 | H24: =GETPIVOTDATA("Attrited",$D$22,"JobLevel",2)/GETPIVOTDATA("Average",$D$22,"JobLevel",2) -> 0.0094506326
D25: 3 | E25: 218 | F25: 9817.2523 | G25: 32 | H25: =GETPIVOTDATA("Attrited",$D$22,"JobLevel",3)/GETPIVOTDATA("Average",$D$22,"JobLevel",3) -> 0.0032595679
D26: 4 | E26: 106 | F26: 15503.783 | G26: 5 | H26: =GETPIVOTDATA("Attrited",$D$22,"JobLevel",4)/GETPIVOTDATA("Average",$D$22,"JobLevel",4) -> 0.00032250193
D27: 5 | E27: 69 | F27: 19191.826 | G27: 5 | H27: =GETPIVOTDATA("Attrited",$D$22,"JobLevel",5)/GETPIVOTDATA("Average",$D$22,"JobLevel",5) -> 0.00026052758
D28: Grand Total | E28: 1470 | F28: 6502.9313 | G28: 237

Sheet High Risk Employee
C1: HIGH RISK EMPLOYEE TRACKER — Active Employees at Risk of Leaving
C2: Criteria: Active Employees with OverTime=Yes AND JobSatisfaction ≤ 2 | Immediate HR Intervention Recommended
F5: HIGH RISK TOTAL | G5: DEPT AFFECTED | H5: AVG SALARY | I5: 📅 AVG TENURE
F6: =COUNTA(C12:C108) -> 97 | G6: 3 | H6: =AVERAGE(H12:H108) -> 7239.0103 | I6: =AVERAGE(K12:K108) -> 8.1030928
C11: Age | D11: Department | E11: EmployeeNumber | F11: JobRole | G11: JobSatisfaction | H11: MonthlyIncome | I11: OverTime | J11: WorkLifeBalance | K11: YearsAtCompany | L11: YearsSinceLastPromotion | M11: RiskScore
C12: 55 | D12: Research & Development | E12: 1278 | F12: Healthcare Representative | G12: 2 | H12: 13577 | I12: Yes | J12: 3 | K12: 33 | L12: 15 | M12: 18
C13: 39 | D13: Research & Development | E13: 1307 | F13: Manager | G13: 2 | H13: 17123 | I13: Yes | J13: 3 | K13: 19 | L13: 15 | M13: 18
C14: 56 | D14: Research & Development | E14: 1373 | F14: Manufacturing Director | G14: 2 | H14: 13402 | I14: Yes | J14: 3 | K14: 19 | L14: 15 | M14: 18
C15: 46 | D15: Research & Development | E15: 124 | F15: Healthcare Representative | G15: 1 | H15: 10673 | I15: Yes | J15: 2 | K15: 10 | L15: 9 | M15: 17
C16: 39 | D16: Research & Development | E16: 429 | F16: Manager | G16: 1 | H16: 17068 | I16: Yes | J16: 3 | K16: 21 | L16: 11 | M16: 17
C17: 47 | D17: Research & Development | E17: 1827 | F17: Manufacturing Director | G17: 2 | H17: 10333 | I17: Yes | J17: 3 | K17: 22 | L17: 14 | M17: 17
C18: 51 | D18: Sales | E18: 1282 | F18: Manager | G18: 2 | H18: 19847 | I18: Yes | J18: 2 | K18: 29 | L18: 11 | M18: 16
C19: 32 | D19: Sales | E19: 436 | F19: Sales Executive | G19: 2 | H19: 5228 | I19: Yes | J19: 3 | K19: 13 | L19: 11 | M19: 14
C20: 27 | D20: Research & Development | E20: 1244 | F20: Research Scientist | G20: 1 | H20: 2235 | I20: Yes | J20: 2 | K20: 9 | L20: 6 | M20: 14
C21: 42 | D21: Research & Development | E21: 351 | F21: Laboratory Technician | G21: 1 | H21: 2593 | I21: Yes | J21: 3 | K21: 9 | L21: 7 | M21: 13
C22: 38 | D22: Sales | E22: 382 | F22: Sales Executive | G22: 1 | H22: 5605 | I22: Yes | J22: 3 | K22: 8 | L22: 7 | M22: 13
C23: 42 | D23: Research & Development | E23: 605 | F23: Manufacturing Director | G23: 1 | H23: 7406 | I23: Yes | J23: 2 | K23: 10 | L23: 5 | M23: 13
... C108: 33 | D108: Human Resources | E108: 910 | F108: Human Resources | G108: 2 | H108: 2277 | I108: Yes | J108: 4 | K108: 4 | L108: 0 | M108: 1
C112: Risk Score ≥ 10: Critical | Risk Score 6-9: High | Risk Score < 6: Moderate | Formula: (3-JobSat)×3 + (3-WLB)×2 + YrsNoPromotion
